README.rst
setup.py
LeakDB.egg-info/PKG-INFO
LeakDB.egg-info/SOURCES.txt
LeakDB.egg-info/dependency_links.txt
LeakDB.egg-info/requires.txt
LeakDB.egg-info/top_level.txt
leakdb/__init__.py
leakdb/exceptions.py
leakdb/log.py
leakdb/queue.py
leakdb/settings.py
leakdb/storage.py
leakdb/transport.py