Metadata-Version: 1.1
Name: LeakDB
Version: 0.1
Summary: LeakDB is a very simple and fast key value store for Python
Home-page: https://github.com/Lujeni/LeakDB
Author: Lujeni
Author-email: julien@thebault.co
License: UNKNOWN
Platform: UNKNOWN
Classifier: Programming Language :: Python :: 2.7
Classifier: Development Status :: 1 - Planning
Classifier: License :: OSI Approved :: BSD License
Classifier: Natural Language :: English
Classifier: Operating System :: Unix
